pycaret/__init__.py
pycaret/datasets.py
pycaret/distributions.py
pycaret/anomaly/__init__.py
pycaret/anomaly/functional.py
pycaret/anomaly/oop.py
pycaret/classification/__init__.py
pycaret/classification/functional.py
pycaret/classification/oop.py
pycaret/clustering/__init__.py
pycaret/clustering/functional.py
pycaret/clustering/oop.py
pycaret/containers/__init__.py
pycaret/containers/base_container.py
pycaret/containers/metrics/__init__.py
pycaret/containers/metrics/anomaly.py
pycaret/containers/metrics/base_metric.py
pycaret/containers/metrics/classification.py
pycaret/containers/metrics/clustering.py
pycaret/containers/metrics/regression.py
pycaret/containers/metrics/time_series.py
pycaret/containers/models/__init__.py
pycaret/containers/models/anomaly.py
pycaret/containers/models/base_model.py
pycaret/containers/models/classification.py
pycaret/containers/models/clustering.py
pycaret/containers/models/regression.py
pycaret/containers/models/time_series.py
pycaret/internal/__init__.py
pycaret/internal/cloudpickle_compat.py
pycaret/internal/cuml_wrappers.py
pycaret/internal/distributions.py
pycaret/internal/logging.py
pycaret/internal/memory.py
pycaret/internal/meta_estimators.py
pycaret/internal/metrics.py
pycaret/internal/persistence.py
pycaret/internal/pipeline.py
pycaret/internal/tunable.py
pycaret/internal/validation.py
pycaret/internal/display/__init__.py
pycaret/internal/display/display.py
pycaret/internal/display/display_backend.py
pycaret/internal/display/display_component.py
pycaret/internal/display/progress_bar.py
pycaret/internal/parallel/__init__.py
pycaret/internal/parallel/parallel_backend.py
pycaret/internal/patches/__init__.py
pycaret/internal/patches/pyod.py
pycaret/internal/patches/sklearn.py
pycaret/internal/patches/yellowbrick.py
pycaret/internal/plots/__init__.py
pycaret/internal/plots/helper.py
pycaret/internal/plots/residual_plots.py
pycaret/internal/plots/time_series.py
pycaret/internal/plots/yellowbrick.py
pycaret-3.3.0.dist-info/LICENSE
pycaret-3.3.0.dist-info/METADATA
pycaret-3.3.0.dist-info/WHEEL
pycaret-3.3.0.dist-info/top_level.txt
pycaret-3.3.0.dist-info/RECORD
