Metadata-Version: 2.1
Name: pycaret
Version: 3.3.0
Summary: PyCaret - An open source, low-code machine learning library in Python.
Home-page: https://github.com/pycaret/pycaret
Author: Moez Ali
Author-email: moez.ali@queensu.ca
License: MIT
Classifier: License :: OSI Approved :: MIT License
Classifier: Programming Language :: Python :: 3.9
Classifier: Programming Language :: Python :: 3.10
Classifier: Programming Language :: Python :: 3.11
Classifier: Topic :: Scientific/Engineering :: Artificial Intelligence
Classifier: License :: OSI Approved :: MIT License
Classifier: Operating System :: OS Independent
Requires-Python: >=3.9
License-File: LICENSE
Requires-Dist: ipython (>=5.5.0)
Requires-Dist: ipywidgets (>=7.6.5)
Requires-Dist: tqdm (>=4.62.0)
Requires-Dist: numpy (<1.27,>=1.21)
Requires-Dist: pandas (<2.2.0)
Requires-Dist: jinja2 (>=3)
Requires-Dist: scipy (<=1.11.4,>=1.6.1)
Requires-Dist: joblib (>=1.2.0)
Requires-Dist: scikit-learn (>1.4.0)
Requires-Dist: pyod (>=1.1.3)
Requires-Dist: imbalanced-learn (>=0.12.0)
Requires-Dist: category-encoders (>=2.4.0)
Requires-Dist: lightgbm (>=3.0.0)
Requires-Dist: numba (>=0.55.0)
Requires-Dist: requests (>=2.27.1)
Requires-Dist: psutil (>=5.9.0)
Requires-Dist: markupsafe (>=2.0.1)
Requires-Dist: importlib-metadata (>=4.12.0)
Requires-Dist: nbformat (>=4.2.0)
Requires-Dist: cloudpickle
Requires-Dist: deprecation (>=2.1.0)
Requires-Dist: xxhash
Requires-Dist: matplotlib (<3.8.0)
Requires-Dist: scikit-plot (>=0.3.7)
Requires-Dist: yellowbrick (>=1.4)
Requires-Dist: plotly (>=5.14.0)
Requires-Dist: kaleido (>=0.2.1)
Requires-Dist: schemdraw (==0.15)
Requires-Dist: plotly-resampler (>=0.8.3.1)
Requires-Dist: statsmodels (>=0.12.1)
Requires-Dist: sktime (>=0.26.0)
Requires-Dist: tbats (>=1.1.3)
Requires-Dist: pmdarima (>=2.0.4)
Requires-Dist: wurlitzer ; platform_system != "Windows"
Provides-Extra: analysis
Requires-Dist: shap (>=0.44.0) ; extra == 'analysis'
Requires-Dist: interpret (>=0.2.7) ; extra == 'analysis'
Requires-Dist: umap-learn (>=0.5.2) ; extra == 'analysis'
Requires-Dist: pyyaml (==5.3.1) ; extra == 'analysis'
Requires-Dist: ydata-profiling (>=4.3.1) ; extra == 'analysis'
Requires-Dist: explainerdashboard (>=0.3.8) ; extra == 'analysis'
Requires-Dist: fairlearn (==0.7.0) ; extra == 'analysis'
Provides-Extra: full
Requires-Dist: shap (>=0.44.0) ; extra == 'full'
Requires-Dist: interpret (>=0.2.7) ; extra == 'full'
Requires-Dist: umap-learn (>=0.5.2) ; extra == 'full'
Requires-Dist: pyyaml (==5.3.1) ; extra == 'full'
Requires-Dist: ydata-profiling (>=4.3.1) ; extra == 'full'
Requires-Dist: explainerdashboard (>=0.3.8) ; extra == 'full'
Requires-Dist: fairlearn (==0.7.0) ; extra == 'full'
Requires-Dist: kmodes (>=0.11.1) ; extra == 'full'
Requires-Dist: mlxtend (>=0.19.0) ; extra == 'full'
Requires-Dist: statsforecast (<1.6.0,>=0.5.5) ; extra == 'full'
Requires-Dist: hyperopt (>=0.2.7) ; extra == 'full'
Requires-Dist: optuna (>=3.0.0) ; extra == 'full'
Requires-Dist: scikit-optimize (>=0.9.0) ; extra == 'full'
Requires-Dist: mlflow (>=2.0.0) ; extra == 'full'
Requires-Dist: gradio (>=3.50.2) ; extra == 'full'
Requires-Dist: boto3 (>=1.24.56) ; extra == 'full'
Requires-Dist: fastapi ; extra == 'full'
Requires-Dist: uvicorn (>=0.17.6) ; extra == 'full'
Requires-Dist: m2cgen (>=0.9.0) ; extra == 'full'
Requires-Dist: evidently ; extra == 'full'
Requires-Dist: fugue ; extra == 'full'
Requires-Dist: flask ; extra == 'full'
Requires-Dist: Werkzeug (<3.0,>=2.2) ; extra == 'full'
Requires-Dist: triad (<0.9.2) ; extra == 'full'
Requires-Dist: pytest (<8.0.0) ; extra == 'full'
Requires-Dist: moto (<5.0.0) ; extra == 'full'
Requires-Dist: fugue[dask] ; extra == 'full'
Requires-Dist: dash[testing] ; extra == 'full'
Requires-Dist: scikit-learn-intelex (>=2023.0.1) ; (platform_machine == "x86_64" or platform_machine == "AMD64") and extra == 'full'
Requires-Dist: catboost (>=0.23.2) ; (platform_system != "Darwin") and extra == 'full'
Requires-Dist: catboost (<1.2,>=0.23.2) ; (platform_system == "Darwin") and extra == 'full'
Requires-Dist: xgboost (>=1.1.0) ; (python_version != "3.11" or platform_system != "Windows") and extra == 'full'
Requires-Dist: tune-sklearn (>=0.2.1) ; (python_version != "3.11" or platform_system != "Windows") and extra == 'full'
Requires-Dist: ray[tune] (>=1.0.0) ; (python_version != "3.11" or platform_system != "Windows") and extra == 'full'
Provides-Extra: mlops
Requires-Dist: mlflow (>=2.0.0) ; extra == 'mlops'
Requires-Dist: gradio (>=3.50.2) ; extra == 'mlops'
Requires-Dist: boto3 (>=1.24.56) ; extra == 'mlops'
Requires-Dist: fastapi ; extra == 'mlops'
Requires-Dist: uvicorn (>=0.17.6) ; extra == 'mlops'
Requires-Dist: m2cgen (>=0.9.0) ; extra == 'mlops'
Requires-Dist: evidently ; extra == 'mlops'
Provides-Extra: models
Requires-Dist: kmodes (>=0.11.1) ; extra == 'models'
Requires-Dist: mlxtend (>=0.19.0) ; extra == 'models'
Requires-Dist: statsforecast (<1.6.0,>=0.5.5) ; extra == 'models'
Requires-Dist: scikit-learn-intelex (>=2023.0.1) ; (platform_machine == "x86_64" or platform_machine == "AMD64") and extra == 'models'
Requires-Dist: catboost (>=0.23.2) ; (platform_system != "Darwin") and extra == 'models'
Requires-Dist: catboost (<1.2,>=0.23.2) ; (platform_system == "Darwin") and extra == 'models'
Requires-Dist: xgboost (>=1.1.0) ; (python_version != "3.11" or platform_system != "Windows") and extra == 'models'
Provides-Extra: parallel
Requires-Dist: fugue ; extra == 'parallel'
Requires-Dist: flask ; extra == 'parallel'
Requires-Dist: Werkzeug (<3.0,>=2.2) ; extra == 'parallel'
Requires-Dist: triad (<0.9.2) ; extra == 'parallel'
Provides-Extra: test
Requires-Dist: pytest (<8.0.0) ; extra == 'test'
Requires-Dist: moto (<5.0.0) ; extra == 'test'
Requires-Dist: fugue[dask] ; extra == 'test'
Requires-Dist: dash[testing] ; extra == 'test'
Provides-Extra: tuners
Requires-Dist: hyperopt (>=0.2.7) ; extra == 'tuners'
Requires-Dist: optuna (>=3.0.0) ; extra == 'tuners'
Requires-Dist: scikit-optimize (>=0.9.0) ; extra == 'tuners'
Requires-Dist: tune-sklearn (>=0.2.1) ; (python_version != "3.11" or platform_system != "Windows") and extra == 'tuners'
Requires-Dist: ray[tune] (>=1.0.0) ; (python_version != "3.11" or platform_system != "Windows") and extra == 'tuners'
